odoo/addons/account_multicompany_easy_creation/README.rst
odoo/addons/account_multicompany_easy_creation/__init__.py
odoo/addons/account_multicompany_easy_creation/__manifest__.py
odoo/addons/account_multicompany_easy_creation/i18n/account_multicompany_easy_creation.pot
odoo/addons/account_multicompany_easy_creation/i18n/es.po
odoo/addons/account_multicompany_easy_creation/i18n/it.po
odoo/addons/account_multicompany_easy_creation/models/__init__.py
odoo/addons/account_multicompany_easy_creation/models/res_company.py
odoo/addons/account_multicompany_easy_creation/readme/CONTRIBUTORS.md
odoo/addons/account_multicompany_easy_creation/readme/DESCRIPTION.md
odoo/addons/account_multicompany_easy_creation/readme/USAGE.md
odoo/addons/account_multicompany_easy_creation/security/ir.model.access.csv
odoo/addons/account_multicompany_easy_creation/static/description/icon.png
odoo/addons/account_multicompany_easy_creation/static/description/index.html
odoo/addons/account_multicompany_easy_creation/tests/__init__.py
odoo/addons/account_multicompany_easy_creation/tests/test_easy_creation.py
odoo/addons/account_multicompany_easy_creation/wizards/__init__.py
odoo/addons/account_multicompany_easy_creation/wizards/multicompany_easy_creation.py
odoo/addons/account_multicompany_easy_creation/wizards/multicompany_easy_creation.xml
odoo_addon_account_multicompany_easy_creation-18.0.1.0.0.2.dist-info/METADATA
odoo_addon_account_multicompany_easy_creation-18.0.1.0.0.2.dist-info/WHEEL
odoo_addon_account_multicompany_easy_creation-18.0.1.0.0.2.dist-info/top_level.txt
odoo_addon_account_multicompany_easy_creation-18.0.1.0.0.2.dist-info/RECORD
